jptrade.py
jptrade-1.0.0.dist-info/METADATA
jptrade-1.0.0.dist-info/WHEEL
jptrade-1.0.0.dist-info/entry_points.txt
jptrade-1.0.0.dist-info/top_level.txt
jptrade-1.0.0.dist-info/RECORD
