Metadata-Version: 2.1
Name: jptrade
Version: 1.0.0
Summary: A package for visualizing bilateral import between Japan and any country
Home-page: https://github.com/noboru-knm/World-Trade-Visualization
Author: shotaro suzuki
License: UNKNOWN
Project-URL: Bug Tracker, https://github.com/noboru-knm/World-Trade-Visualization
Platform: UNKNOWN
Classifier: Programming Language :: Python :: 3
Classifier: License :: OSI Approved :: MIT License
Classifier: Operating System :: OS Independent
Requires-Python: >=3.7
